phishnet_api_v3/__init__.py
phishnet_api_v3/api_client.py
phishnet_api_v3/decorators.py
phishnet_api_v3/exceptions.py
phishnet_api_v3/settings.py
phishnet_api_v3/validators.py
phishnet_api_v3-0.1.0.dist-info/LICENSE
phishnet_api_v3-0.1.0.dist-info/WHEEL
phishnet_api_v3-0.1.0.dist-info/METADATA
phishnet_api_v3-0.1.0.dist-info/RECORD
