Metadata-Version: 2.1
Name: phishnet-api-v3
Version: 0.1.0
Summary: Python3 client to interface with v3 of the api.phish.net REST endpoints.
Home-page: https://github.com/jflaherty/phishnet_api_v3
Keywords: Phish,REST,API
Author: Jay Flaherty
Author-email: jayflaherty@gmail.com
Requires-Python: >=3.5,<4.0
Classifier: Programming Language :: Python :: 3
Classifier: Programming Language :: Python :: 3.5
Classifier: Programming Language :: Python :: 3.6
Classifier: Programming Language :: Python :: 3.7
Classifier: Programming Language :: Python :: 3.8
Requires-Dist: python-dotenv (>=0.10.3,<0.11.0)
Requires-Dist: requests (>=2.22.0,<3.0.0)
Project-URL: Repository, https://github.com/jflaherty/phishnet_api_v3
